{"version":1,"resource":"vscode-remote://wsl%2Bubuntu/home/murkenne/coursework/Zoo%20animals/about.html","entries":[{"id":"jl2E.html","timestamp":1678748425277},{"id":"KHrO.html","timestamp":1678749259413},{"id":"mUZB.html","timestamp":1678749325353},{"id":"ZDjX.html","timestamp":1678749994563},{"id":"6vuz.html","timestamp":1678750012433},{"id":"DLuX.html","timestamp":1678750963273},{"id":"86d7.html","timestamp":1678751216553},{"id":"j9Ih.html","timestamp":1678751906423},{"id":"Uu5b.html","timestamp":1678752497703},{"id":"v84h.html","timestamp":1678762921403},{"id":"47cq.html","timestamp":1678763675423}]}